avilla/console/__init__.py
avilla/console/account.py
avilla/console/backend.py
avilla/console/capability.py
avilla/console/element.py
avilla/console/perform/__init__.py
avilla/console/perform/action/activity.py
avilla/console/perform/action/message.py
avilla/console/perform/action/profile.py
avilla/console/perform/context.py
avilla/console/perform/event/message.py
avilla/console/perform/message/deserialize.py
avilla/console/perform/message/serialize.py
avilla/console/protocol.py
avilla/console/service.py
avilla/core/__init__.py
avilla/core/_runtime.py
avilla/core/account.py
avilla/core/application.py
avilla/core/builtins/__init__.py
avilla/core/builtins/capability.py
avilla/core/builtins/command/__init__.py
avilla/core/builtins/command/saya.py
avilla/core/builtins/resource_fetch.py
avilla/core/context/__init__.py
avilla/core/context/_roles.py
avilla/core/context/_selector.py
avilla/core/dispatchers.py
avilla/core/elements.py
avilla/core/event.py
avilla/core/exceptions.py
avilla/core/graia.py
avilla/core/message.py
avilla/core/metadata.py
avilla/core/platform.py
avilla/core/protocol.py
avilla/core/py.typed
avilla/core/request.py
avilla/core/resource.py
avilla/core/ryanvk/__init__.py
avilla/core/ryanvk/behavior/__init__.py
avilla/core/ryanvk/behavior/query.py
avilla/core/ryanvk/collector/__init__.py
avilla/core/ryanvk/collector/account.py
avilla/core/ryanvk/collector/application.py
avilla/core/ryanvk/collector/base.py
avilla/core/ryanvk/collector/context.py
avilla/core/ryanvk/collector/protocol.py
avilla/core/ryanvk/descriptor/__init__.py
avilla/core/ryanvk/descriptor/query.py
avilla/core/ryanvk/endpoint/__init__.py
avilla/core/ryanvk/endpoint/launart.py
avilla/core/ryanvk/overload/__init__.py
avilla/core/ryanvk/overload/metadata.py
avilla/core/ryanvk/overload/target.py
avilla/core/ryanvk/staff.py
avilla/core/ryanvk/util.py
avilla/core/selector.py
avilla/core/service.py
avilla/core/tools/__init__.py
avilla/core/tools/filter.py
avilla/core/typing.py
avilla_workspace-0.dist-info/METADATA
avilla_workspace-0.dist-info/WHEEL
avilla_workspace-0.dist-info/licenses/LICENSE
avilla_workspace-0.dist-info/RECORD
