Metadata-Version: 2.1
Name: avilla-workspace
Version: 0
Requires-Python: >=3.9
Requires-Dist: graia-broadcast>=0.23.1
Requires-Dist: graia-amnesia>=0.9.0
Requires-Dist: creart>=0.3.0
Requires-Dist: graia-saya>=0.0.18
Requires-Dist: launart>=0.8.2
Requires-Dist: loguru>=0.6.0
Requires-Dist: aiohttp>=3.8.1
Requires-Dist: nonebot2>=2.0.1
Requires-Dist: wsproto>=1.2.0
Requires-Dist: starlette>=0.34.0
Requires-Dist: uvicorn>=0.25.0
Requires-Dist: nonechat<1.0.0,>=0.2.0
Requires-Dist: arclet-alconna>=1.7.16
Requires-Dist: arclet-alconna-tools>=0.6.5
Requires-Dist: pygtrie>=2.5.0
Requires-Dist: selectolax>=0.3.16
Requires-Dist: satori-python>=0.9.2
